[
    {
        "id": 19,
        "data": {
            "title": "Fortnite LEGO",
            "timer_default": "10",
            "notes": "22.5, 27.8 - 28.1",
            "keys": [
                {
                    "key": "w",
                    "pressed": "7",
                    "onetap": false,
                    "random": false,
                    "min": "2",
                    "max": "10"
                },
                {
                    "key": "d",
                    "pressed": "7",
                    "onetap": false,
                    "random": true,
                    "min": "4",
                    "max": "10"
                },
                {
                    "key": "s",
                    "pressed": "7",
                    "onetap": false,
                    "random": false,
                    "min": "3",
                    "max": "12"
                },
                {
                    "key": "a",
                    "pressed": "7",
                    "onetap": false,
                    "random": true,
                    "min": "2",
                    "max": "14"
                },
                {
                    "key": "space",
                    "pressed": "2",
                    "onetap": false,
                    "random": true,
                    "min": "2",
                    "max": "4"
                },
                {
                    "key": "click",
                    "pressed": "1",
                    "onetap": false,
                    "random": true,
                    "min": "",
                    "max": ""
                }
            ]
        }
    },
    {
        "id": 28,
        "data": {
            "title": "Teste Click",
            "timer_default": "",
            "notes": "",
            "keys": [
                {
                    "key": "click",
                    "pressed": "",
                    "onetap": false,
                    "random": true,
                    "min": "",
                    "max": ""
                },
                {
                    "key": "",
                    "pressed": "",
                    "onetap": false,
                    "random": false,
                    "min": "",
                    "max": ""
                }
            ]
        }
    },
    {
        "id": 53,
        "data": {
            "title": "Fortnite FESTIVAL",
            "timer_default": "20",
            "notes": "28.2, 32.7",
            "keys": [
                {
                    "key": "w",
                    "pressed": "",
                    "onetap": false,
                    "random": true,
                    "min": "3",
                    "max": "10"
                },
                {
                    "key": "a",
                    "pressed": "",
                    "onetap": false,
                    "random": true,
                    "min": "2",
                    "max": "12"
                },
                {
                    "key": "b",
                    "pressed": "",
                    "onetap": true,
                    "random": true,
                    "min": "15",
                    "max": "40"
                },
                {
                    "key": "d",
                    "pressed": "",
                    "onetap": false,
                    "random": true,
                    "min": "4",
                    "max": "14"
                },
                {
                    "key": "space",
                    "pressed": "",
                    "onetap": false,
                    "random": true,
                    "min": "2",
                    "max": "5"
                },
                {
                    "key": "b",
                    "pressed": "",
                    "onetap": true,
                    "random": true,
                    "min": "20",
                    "max": "60"
                },
                {
                    "key": "click",
                    "pressed": "",
                    "onetap": false,
                    "random": true,
                    "min": "",
                    "max": ""
                },
                {
                    "key": "s",
                    "pressed": "",
                    "onetap": false,
                    "random": true,
                    "min": "1",
                    "max": "9"
                },
                {
                    "key": "b",
                    "pressed": "",
                    "onetap": true,
                    "random": false,
                    "min": "10",
                    "max": "30"
                }
            ]
        }
    }
]